pySwitch/__init__.py
PythonicSwitch-1.0.3.dist-info/LICENSE
PythonicSwitch-1.0.3.dist-info/METADATA
PythonicSwitch-1.0.3.dist-info/WHEEL
PythonicSwitch-1.0.3.dist-info/top_level.txt
PythonicSwitch-1.0.3.dist-info/RECORD
