Metadata-Version: 2.1
Name: PythonicSwitch
Version: 1.0.3
Summary: A pythonic way to implement switch-case
Home-page: https://github.com/DrSparky-2007/PythonicSwitchCase
Author: DrSparky-2007
Author-email: adityaiyer2007@gmail.com
License: UNKNOWN
Keywords: PythonicSwitch,Switch case,Switch statement
Platform: UNKNOWN
Classifier: Programming Language :: Python :: 3
Classifier: License :: OSI Approved :: MIT License
Classifier: Operating System :: OS Independent
